{
  "id": 343,
  "question_type": "single_select_4orless",
  "question": "What is the effect of density altitude reading at a fixed point when air density drops?",
  "image": null,
  "options": [
    {
      "key": "A",
      "text": "The density altitude reading increases"
    },
    {
      "key": "B",
      "text": "The density altitude decreases"
    },
    {
      "key": "C",
      "text": "The density altitude stays the same"
    }
  ],
  "correct_answers": [
    "A"
  ],
  "answer": "A",
  "knowledge_area": "Navigation and Meteorology",
  "syllabus_reference": "040 02 02",
  "metadata": {
    "knowledge_area": "Navigation and Meteorology",
    "syllabus_reference": "040 02 02"
  },
  "classification_confidence": {
    "knowledge_area": 1.0,
    "syllabus_reference": 1.0
  },
  "classification_source": "manual",
  "classification_notes": "Density altitude rises as density falls."
}